mockish/__init__.py
mockish/__version__.py
mockish/constants.py
mockish/mockish.py
mockish/models.py
mockish/py.typed
mockish/__pycache__/__init__.cpython-310.pyc
mockish/__pycache__/__version__.cpython-310.pyc
mockish/__pycache__/constants.cpython-310.pyc
mockish/__pycache__/mockish.cpython-310.pyc
mockish/__pycache__/models.cpython-310.pyc
mockish/httpx/__init__.py
mockish/httpx/response.py
mockish/httpx/__pycache__/__init__.cpython-310.pyc
mockish/httpx/__pycache__/response.cpython-310.pyc
mockish/requests/__init__.py
mockish/requests/response.py
mockish/requests/__pycache__/__init__.cpython-310.pyc
mockish/requests/__pycache__/response.cpython-310.pyc
mockish-0.1.1.dist-info/LICENSE
mockish-0.1.1.dist-info/METADATA
mockish-0.1.1.dist-info/WHEEL
mockish-0.1.1.dist-info/entry_points.txt
mockish-0.1.1.dist-info/top_level.txt
mockish-0.1.1.dist-info/RECORD
