Metadata-Version: 2.1
Name: mockish
Version: 0.1.1
Summary: A thin layer of sugar atop Python's mock.
Author-email: Donald Mellenbruch <hello@Fresh2.dev>
License: GNU GENERAL PUBLIC LICENSE
Project-URL: Homepage, https://www.Fresh2.dev/code/r/mockish/i
Project-URL: Repository, https://www.github.com/fresh2dev/mockish
Project-URL: Funding, https://www.Fresh2.dev/funding
Classifier: Programming Language :: Python :: 3
Requires-Python: >=3.7
License-File: LICENSE
Requires-Dist: requests (==2.*)
Requires-Dist: httpx (==0.*)
Requires-Dist: typing-extensions ; python_version < "3.10"
Provides-Extra: dev
Requires-Dist: python-lsp-server[rope] (==1.*) ; extra == 'dev'
Requires-Dist: pylint (==2.*) ; extra == 'dev'
Requires-Dist: pylint-pytest (==1.*) ; extra == 'dev'
Requires-Dist: mypy[reports] (==1.*) ; extra == 'dev'
Requires-Dist: ruff (==0.*) ; extra == 'dev'
Requires-Dist: black[jupyter] (==23.*) ; extra == 'dev'
Requires-Dist: isort (==5.*) ; extra == 'dev'
Requires-Dist: bump2version (==1.*) ; extra == 'dev'
Requires-Dist: pdbpp ; extra == 'dev'
Requires-Dist: ipykernel ; extra == 'dev'
Requires-Dist: ipywidgets ; extra == 'dev'
Requires-Dist: ipython ; extra == 'dev'
Provides-Extra: docs
Requires-Dist: mkdocs (==1.*) ; extra == 'docs'
Requires-Dist: mkdocs-material (==9.*) ; extra == 'docs'
Requires-Dist: mkdocs-jupyter (==0.24.*) ; extra == 'docs'
Requires-Dist: mkdocstrings[python] (==0.20.*) ; extra == 'docs'
Requires-Dist: mkdocs-autorefs (==0.*) ; extra == 'docs'
Requires-Dist: mkdocs-include-dir-to-nav (==1.*) ; extra == 'docs'
Provides-Extra: tests
Requires-Dist: pytest (==7.*) ; extra == 'tests'
Requires-Dist: pytest-cov (==4.*) ; extra == 'tests'
Requires-Dist: pytest-html (==3.*) ; extra == 'tests'
Requires-Dist: pytest-sugar (==0.*) ; extra == 'tests'
Requires-Dist: pytest-custom-exit-code (==0.3.*) ; extra == 'tests'
Requires-Dist: pylint (==2.*) ; extra == 'tests'
Requires-Dist: pylint-pytest (==1.*) ; extra == 'tests'
Requires-Dist: packaging (==23.*) ; extra == 'tests'
